{
    "version": "https://jsonfeed.org/version/1",
    "title": "Roy Tang",
	"description": "Roy Tang's blog. Programmer, engineer, scientist, critic, gamer, dreamer, and kid-at-heart. Randomly amazed.",
    "home_page_url": "https://mirror.roytang.net/",
    "feed_url": "https://mirror.roytang.net/feed.json",
	"author": {
		"name": "Roy Tang",
		"url": "https://roytang.net"
    },
    "items": [
        
        {
            "id": "https://mirror.roytang.net/2012/08/240571677438787584/",
            "url": "https://mirror.roytang.net/2012/08/240571677438787584/",
            "path": "/2012/08/240571677438787584/",
            "title": "",
            "content_html": "\u003cp\u003eWhat qualities do really bad programmers share? \u003ca href=\"http://qr.ae/8UW38\"\u003ehttp://qr.ae/8UW38\u003c/a\u003e\u003c/p\u003e\n",
            "summary": "What qualities do really bad programmers share? http://qr.ae/8UW38",
            "date_published": "2012-08-28T22:08:52+00:00",
            "date_modified": "2019-09-01T15:11:18+08:00",
            "section": "notes",
            "source_path": "notes/2012/08/240571677438787584.md"
            
            , "syndicated": [{"type":"twitter","url":"https://twitter.com/roytang/statuses/240571677438787584/"}]
            
            
            }
        
        , {
            "id": "https://mirror.roytang.net/2012/08/240454324378013696/",
            "url": "https://mirror.roytang.net/2012/08/240454324378013696/",
            "path": "/2012/08/240454324378013696/",
            "title": "",
            "content_html": "\u003cp\u003eThat feel when you\u0026rsquo;re able to plug in a usb device on the first try\u003c/p\u003e\n",
            "summary": "That feel when you\u0026rsquo;re able to plug in a usb device on the first try",
            "date_published": "2012-08-28T14:22:33+00:00",
            "date_modified": "2019-09-01T15:11:18+08:00",
            "section": "notes",
            "source_path": "notes/2012/08/240454324378013696.md"
            
            , "syndicated": [{"type":"twitter","url":"https://twitter.com/roytang/statuses/240454324378013696/"}]
            
            
            }
        
        , {
            "id": "https://mirror.roytang.net/2012/08/240450718916558848/",
            "url": "https://mirror.roytang.net/2012/08/240450718916558848/",
            "path": "/2012/08/240450718916558848/",
            "title": "",
            "content_html": "\u003cp\u003eCelebrate Street Fighter\u0026rsquo;s 25th anniversary by using a Street Fighter animated gif as your twitter avatar! \u003ca href=\"http://www.capcom-unity.com/xantista/go/gallery/view/3559513?pref_tab=photos\u0026amp;no_redir=1\"\u003ehttp://www.capcom-unity.com/xantista/go/gallery/view/3559513?pref_tab=photos\u0026amp;no_redir=1\u003c/a\u003e\u003c/p\u003e\n",
            "summary": "Celebrate Street Fighter\u0026rsquo;s 25th anniversary by using a Street Fighter animated gif as your twitter avatar! http://www.capcom-unity.com/xantista/go/gallery/view/3559513?pref_tab=photos\u0026amp;no_redir=1",
            "date_published": "2012-08-28T14:08:13+00:00",
            "date_modified": "2019-09-01T15:11:18+08:00",
            "section": "notes",
            "source_path": "notes/2012/08/240450718916558848.md"
            
            , "syndicated": [{"type":"twitter","url":"https://twitter.com/roytang/statuses/240450718916558848/"}]
            
            
            }
        
        , {
            "id": "https://mirror.roytang.net/2012/08/240450500540129280/",
            "url": "https://mirror.roytang.net/2012/08/240450500540129280/",
            "path": "/2012/08/240450500540129280/",
            "title": "",
            "content_html": "\u003cp\u003eTIL your twitter avatar can be an animated gif. This changes everything!\u003c/p\u003e\n",
            "summary": "TIL your twitter avatar can be an animated gif. This changes everything!",
            "date_published": "2012-08-28T14:07:21+00:00",
            "date_modified": "2019-09-01T15:11:18+08:00",
            "section": "notes",
            "source_path": "notes/2012/08/240450500540129280.md"
            
            , "syndicated": [{"type":"twitter","url":"https://twitter.com/roytang/statuses/240450500540129280/"}]
            
            
            }
        
        , {
            "id": "https://mirror.roytang.net/2012/08/240446312250748929/",
            "url": "https://mirror.roytang.net/2012/08/240446312250748929/",
            "path": "/2012/08/240446312250748929/",
            "title": "",
            "content_html": "\u003cp\u003eWoah there\u0026rsquo;s a Rurouni Kenshin reboot already being serialized!\u003c/p\u003e\n",
            "summary": "Woah there\u0026rsquo;s a Rurouni Kenshin reboot already being serialized!",
            "date_published": "2012-08-28T13:50:42+00:00",
            "date_modified": "2019-09-01T15:11:18+08:00",
            "section": "notes",
            "source_path": "notes/2012/08/240446312250748929.md"
            
            , "syndicated": [{"type":"twitter","url":"https://twitter.com/roytang/statuses/240446312250748929/"}]
            
            
            }
        
        , {
            "id": "https://mirror.roytang.net/2012/08/240103459146305537/",
            "url": "https://mirror.roytang.net/2012/08/240103459146305537/",
            "path": "/2012/08/240103459146305537/",
            "title": "",
            "content_html": "\u003cp\u003e\u003ca href=\"https://twitter.com/wrongwaygoback/\"\u003e@wrongwaygoback\u003c/a\u003e does landing mean simply casting it? Or getting to untap with it?\u003c/p\u003e\n",
            "summary": "@wrongwaygoback does landing mean simply casting it? Or getting to untap with it?",
            "date_published": "2012-08-27T15:08:20+00:00",
            "date_modified": "2020-01-23T05:14:22+08:00",
            "section": "notes",
            "source_path": "notes/2012/08/240103459146305537.md"
            
            , "syndicated": [{"type":"twitter","url":"https://twitter.com/roytang/statuses/240103459146305537/"}]
            
            
            }
        
        , {
            "id": "https://mirror.roytang.net/2012/08/30312221042/",
            "url": "https://mirror.roytang.net/2012/08/30312221042/",
            "path": "/2012/08/30312221042/",
            "title": "",
            "content_html": "\u003cp\u003eNo idea if All New X-Men is going to be any good, but I really like the currently available preview cover.\u003c/p\u003e",
            "summary": "No idea if All New X-Men is going to be any good, but I really like the currently available preview cover.",
            "date_published": "2012-08-27T12:32:51+00:00",
            "date_modified": "2020-01-23T05:24:41+08:00",
            "section": "notes",
            "source_path": "notes/2012/08/30312221042/index.md"
            
            , "syndicated": [{"type":"tumblr","url":"https://tumblr.roytang.net/post/30312221042/no-idea-if-all-new-x-men-is-going-to-be-any-good"},{"type":"twitter","url":"https://twitter.com/roytang/statuses/240064331558027264/"}]
            
            
            }
        
        , {
            "id": "https://mirror.roytang.net/2012/08/239892026122981376/",
            "url": "https://mirror.roytang.net/2012/08/239892026122981376/",
            "path": "/2012/08/239892026122981376/",
            "title": "",
            "content_html": "\u003cp\u003eNothing like a walk through the rain to start off the day\u003c/p\u003e\n",
            "summary": "Nothing like a walk through the rain to start off the day",
            "date_published": "2012-08-27T01:08:10+00:00",
            "date_modified": "2019-09-12T04:21:53+08:00",
            "section": "notes",
            "source_path": "notes/2012/08/239892026122981376.md"
            
            , "syndicated": [{"type":"twitter","url":"https://twitter.com/roytang/statuses/239892026122981376/"},{"type":"facebook","url":"https://www.facebook.com/stephen.roy.tang/posts/10151820876448912"}]
            
            
            }
        
        , {
            "id": "https://mirror.roytang.net/2012/08/239732855352213504/",
            "url": "https://mirror.roytang.net/2012/08/239732855352213504/",
            "path": "/2012/08/239732855352213504/",
            "title": "",
            "content_html": "\u003cp\u003eTop 5 surprises when starting out as a software developer:  My favorite has to be #1\u003c/p\u003e\n",
            "summary": "Top 5 surprises when starting out as a software developer: My favorite has to be #1",
            "date_published": "2012-08-26T14:35:41+00:00",
            "date_modified": "2021-04-17T10:42:41+08:00",
            "section": "links",
            "source_path": "links/2012/08/239732855352213504/index.md"
            , "tags": ["1"]
            , "syndicated": [{"type":"twitter","url":"https://twitter.com/roytang/statuses/239732855352213504/"},{"type":"facebook","url":"https://www.facebook.com/stephen.roy.tang/posts/10151819681878912"}]
            ,"link": "https://henrikwarne.com/2012/08/22/top-5-surprises-when-starting-out-as-a-software-developer/"
            
            }
        
        , {
            "id": "https://mirror.roytang.net/2012/08/239572870966165505/",
            "url": "https://mirror.roytang.net/2012/08/239572870966165505/",
            "path": "/2012/08/239572870966165505/",
            "title": "",
            "content_html": "\u003cp\u003eIn the middle of a Community Season 1 marathon, lolling liberally\u003c/p\u003e\n",
            "summary": "In the middle of a Community Season 1 marathon, lolling liberally",
            "date_published": "2012-08-26T03:59:58+00:00",
            "date_modified": "2019-09-01T15:11:18+08:00",
            "section": "notes",
            "source_path": "notes/2012/08/239572870966165505.md"
            
            , "syndicated": [{"type":"twitter","url":"https://twitter.com/roytang/statuses/239572870966165505/"}]
            
            
            }
        
        , {
            "id": "https://mirror.roytang.net/2012/08/239508152192753665/",
            "url": "https://mirror.roytang.net/2012/08/239508152192753665/",
            "path": "/2012/08/239508152192753665/",
            "title": "",
            "content_html": "\u003cp\u003eWill the Apple patent victory have the unintentional consequence of consumers switching to Samsung? \u003ca href=\"https://plus.google.com/114476892281222708332/posts/246srfbqg6G\u0026amp;followup=https://plus.google.com/114476892281222708332/posts/246srfbqg6G\"\u003ehttps://plus.google.com/114476892281222708332/posts/246srfbqg6G\u0026amp;followup=https://plus.google.com/114476892281222708332/posts/246srfbqg6G\u003c/a\u003e\u003c/p\u003e\n",
            "summary": "Will the Apple patent victory have the unintentional consequence of consumers switching to Samsung? https://plus.google.com/114476892281222708332/posts/246srfbqg6G\u0026amp;followup=https://plus.google.com/114476892281222708332/posts/246srfbqg6G",
            "date_published": "2012-08-25T23:42:47+00:00",
            "date_modified": "2020-08-19T14:11:33+08:00",
            "section": "notes",
            "source_path": "notes/2012/08/239508152192753665.md"
            
            , "syndicated": [{"type":"twitter","url":"https://twitter.com/roytang/statuses/239508152192753665/"},{"type":"facebook","url":"https://www.facebook.com/stephen.roy.tang/posts/10151818503553912"}]
            
            
            }
        
        , {
            "id": "https://mirror.roytang.net/2012/08/239401449803628544/",
            "url": "https://mirror.roytang.net/2012/08/239401449803628544/",
            "path": "/2012/08/239401449803628544/",
            "title": "",
            "content_html": "\u003cp\u003eAmused by the Twitter drama between \u003ca href=\"https://twitter.com/Ssnyder1835/\"\u003e@Ssnyder1835\u003c/a\u003e and \u003ca href=\"https://twitter.com/robertliefeld/\"\u003e@robertliefeld\u003c/a\u003e . I wouldn\u0026rsquo;t mind Snyder taking over Hawkman :D\u003c/p\u003e\n",
            "summary": "Amused by the Twitter drama between @Ssnyder1835 and @robertliefeld . I wouldn\u0026rsquo;t mind Snyder taking over Hawkman :D",
            "date_published": "2012-08-25T16:38:48+00:00",
            "date_modified": "2019-09-01T15:11:18+08:00",
            "section": "notes",
            "source_path": "notes/2012/08/239401449803628544.md"
            
            , "syndicated": [{"type":"twitter","url":"https://twitter.com/roytang/statuses/239401449803628544/"}]
            
            
            }
        
        , {
            "id": "https://mirror.roytang.net/2012/08/239052711406997504/",
            "url": "https://mirror.roytang.net/2012/08/239052711406997504/",
            "path": "/2012/08/239052711406997504/",
            "title": "",
            "content_html": "\u003cp\u003e\u003ca href=\"https://twitter.com/alvinjtang/\"\u003e@alvinjtang\u003c/a\u003e nadownload mo na ung ep? uwi mo na lang bukas lol\u003c/p\u003e\n",
            "summary": "@alvinjtang nadownload mo na ung ep? uwi mo na lang bukas lol",
            "date_published": "2012-08-24T17:33:02+00:00",
            "date_modified": "2021-04-17T04:27:03+08:00",
            "section": "notes",
            "source_path": "notes/2012/08/239052711406997504/index.md"
            
            , "syndicated": [{"type":"twitter","url":"https://twitter.com/roytang/statuses/239052711406997504/"}]
            
            , "comments": [
                { 
                    "url": "https://twitter.com/alvinjtang",
                    "source_file": "comment-20120824-173729-22240ce4-87f3-4b27-ad13-4ad13b975e04.json"
                }, { 
                    "url": "https://twitter.com/roytang",
                    "source_file": "comment-20120824-173812-b26a7403-b57d-45c1-94b7-6b5b222dfac0.json"
                }, { 
                    "url": "https://twitter.com/alvinjtang",
                    "source_file": "comment-20120824-174015-3256c047-2cf6-4d24-bc4a-530dc5bb0628.json"
                }
            ]
            }
        
        , {
            "id": "https://mirror.roytang.net/2012/08/238767136636538881/",
            "url": "https://mirror.roytang.net/2012/08/238767136636538881/",
            "path": "/2012/08/238767136636538881/",
            "title": "",
            "content_html": "\u003cp\u003e@lizbethjane that sounds racist\u003c/p\u003e\n",
            "summary": "@lizbethjane that sounds racist",
            "date_published": "2012-08-23T22:38:16+00:00",
            "date_modified": "2020-01-23T05:14:22+08:00",
            "section": "notes",
            "source_path": "notes/2012/08/238767136636538881.md"
            
            , "syndicated": [{"type":"twitter","url":"https://twitter.com/roytang/statuses/238767136636538881/"}]
            
            
            }
        
        , {
            "id": "https://mirror.roytang.net/2012/08/238646209743552512/",
            "url": "https://mirror.roytang.net/2012/08/238646209743552512/",
            "path": "/2012/08/238646209743552512/",
            "title": "",
            "content_html": "\u003cp\u003eMark Millar enjoyed his Manila visit so much, a couple of pages of the last issue of Supercrooks takes place in Manila: \u003ca href=\"https://i.imgur.com/removed.png\"\u003ehttps://i.imgur.com/removed.png\u003c/a\u003e\u003c/p\u003e\n",
            "summary": "Mark Millar enjoyed his Manila visit so much, a couple of pages of the last issue of Supercrooks takes place in Manila: https://i.imgur.com/removed.png",
            "date_published": "2012-08-23T14:37:44+00:00",
            "date_modified": "2020-08-18T20:10:05+08:00",
            "section": "notes",
            "source_path": "notes/2012/08/238646209743552512/index.md"
            
            , "syndicated": [{"type":"twitter","url":"https://twitter.com/roytang/statuses/238646209743552512/"},{"type":"facebook","url":"https://www.facebook.com/stephen.roy.tang/posts/485372381473272"}]
            
            
            }
        
        , {
            "id": "https://mirror.roytang.net/2012/08/238645354839539712/",
            "url": "https://mirror.roytang.net/2012/08/238645354839539712/",
            "path": "/2012/08/238645354839539712/",
            "title": "",
            "content_html": "\u003cp\u003ePeople of Manila, I loved my signing there so much I shoe-horned 2 pages of Supercrooks #4 into your country. Check it out!\u003c/p\u003e\n",
            "summary": "People of Manila, I loved my signing there so much I shoe-horned 2 pages of Supercrooks #4 into your country. Check it out!",
            "date_published": "2012-08-23T14:34:21+00:00",
            "date_modified": "2020-08-18T20:10:05+08:00",
            "section": "notes",
            "source_path": "notes/2012/08/238645354839539712/index.md"
            , "tags": ["4"]
            , "syndicated": [{"type":"twitter","url":"https://twitter.com/roytang/statuses/238645354839539712/"}]
            
            
            }
        
        , {
            "id": "https://mirror.roytang.net/2012/08/238625172935045120/",
            "url": "https://mirror.roytang.net/2012/08/238625172935045120/",
            "path": "/2012/08/238625172935045120/",
            "title": "",
            "content_html": "\u003cp\u003eAnnoyed by torrents that don\u0026rsquo;t use the proper filenames #firstworldpirateproblems\u003c/p\u003e\n",
            "summary": "Annoyed by torrents that don\u0026rsquo;t use the proper filenames #firstworldpirateproblems",
            "date_published": "2012-08-23T13:14:09+00:00",
            "date_modified": "2019-09-07T03:37:00+08:00",
            "section": "notes",
            "source_path": "notes/2012/08/238625172935045120.md"
            , "tags": ["firstworldpirateproblems"]
            , "syndicated": [{"type":"twitter","url":"https://twitter.com/roytang/statuses/238625172935045120/"}]
            
            
            }
        
        , {
            "id": "https://mirror.roytang.net/2012/08/yn2ke/",
            "url": "https://mirror.roytang.net/2012/08/yn2ke/",
            "path": "/2012/08/yn2ke/",
            "title": "",
            "content_html": "",
            "summary": "",
            "date_published": "2012-08-22T23:12:48+00:00",
            "date_modified": "2020-01-23T03:46:15+08:00",
            "section": "links",
            "source_path": "links/2012/08/yn2ke/index.md"
            , "tags": ["futurama"]
            , "syndicated": [{"type":"reddit","url":"https://reddit.com/r/futurama/comments/yn2ke/jurassic_bark_reference_in_fallout_new_vegas/"}]
            ,"link": "http://steamcommunity.com/sharedfiles/filedetails/?id=91011838"
            
            }
        
        , {
            "id": "https://mirror.roytang.net/2012/08/ymwny/",
            "url": "https://mirror.roytang.net/2012/08/ymwny/",
            "path": "/2012/08/ymwny/",
            "title": "",
            "content_html": "",
            "summary": "",
            "date_published": "2012-08-22T21:23:24+00:00",
            "date_modified": "2020-01-23T03:46:15+08:00",
            "section": "links",
            "source_path": "links/2012/08/ymwny/index.md"
            , "tags": ["gaming"]
            , "syndicated": [{"type":"reddit","url":"https://reddit.com/r/gaming/comments/ymwny/fallout_new_vegas_the_lonesome_road_something/"}]
            ,"link": "http://steamcommunity.com/sharedfiles/filedetails/?id=91011838"
            
            }
        
        , {
            "id": "https://mirror.roytang.net/2012/08/238276907395842048/",
            "url": "https://mirror.roytang.net/2012/08/238276907395842048/",
            "path": "/2012/08/238276907395842048/",
            "title": "",
            "content_html": "\u003cp\u003e\u003ca href=\"https://twitter.com/Woerlan/\"\u003e@Woerlan\u003c/a\u003e It feels really gimmicky, but I\u0026rsquo;ll wait til I read the issue before passing judgment. New52 JL isnt that great though =/\u003c/p\u003e\n",
            "summary": "@Woerlan It feels really gimmicky, but I\u0026rsquo;ll wait til I read the issue before passing judgment. New52 JL isnt that great though =/",
            "date_published": "2012-08-22T14:10:16+00:00",
            "date_modified": "2021-04-17T03:36:10+08:00",
            "section": "notes",
            "source_path": "notes/2012/08/238276907395842048/index.md"
            
            , "syndicated": [{"type":"twitter","url":"https://twitter.com/roytang/statuses/238276907395842048/"}]
            
            , "comments": [
                { 
                    "url": "https://twitter.com/Woerlan",
                    "source_file": "comment-20120822-154219-246234c5-46ef-42c9-9516-f5740c7a74f1.json"
                }, { 
                    "url": "https://twitter.com/roytang",
                    "source_file": "comment-20120822-155209-c06e1030-35a3-4499-93a2-77982a5a49c0.json"
                }, { 
                    "url": "https://twitter.com/Woerlan",
                    "source_file": "comment-20120822-225857-4fd16643-6db9-4367-afec-c1515e23e1e8.json"
                }
            ]
            }
        
        , {
            "id": "https://mirror.roytang.net/2012/08/237915172574998529/",
            "url": "https://mirror.roytang.net/2012/08/237915172574998529/",
            "path": "/2012/08/237915172574998529/",
            "title": "",
            "content_html": "\u003cp\u003eThe final boss in Fallout New Vegas The Lonesome Road was Bane from TDKR!\u003c/p\u003e\n",
            "summary": "The final boss in Fallout New Vegas The Lonesome Road was Bane from TDKR!",
            "date_published": "2012-08-21T14:12:52+00:00",
            "date_modified": "2019-09-12T04:21:53+08:00",
            "section": "notes",
            "source_path": "notes/2012/08/237915172574998529.md"
            
            , "syndicated": [{"type":"twitter","url":"https://twitter.com/roytang/statuses/237915172574998529/"},{"type":"facebook","url":"https://www.facebook.com/stephen.roy.tang/posts/10151808767638912"}]
            
            
            }
        
        , {
            "id": "https://mirror.roytang.net/2012/08/237904909436067840/",
            "url": "https://mirror.roytang.net/2012/08/237904909436067840/",
            "path": "/2012/08/237904909436067840/",
            "title": "",
            "content_html": "\u003cp\u003eSo, the most important question: should we expect Monday-level traffic tomorrow?\u003c/p\u003e\n",
            "summary": "So, the most important question: should we expect Monday-level traffic tomorrow?",
            "date_published": "2012-08-21T13:32:05+00:00",
            "date_modified": "2019-09-12T04:21:53+08:00",
            "section": "notes",
            "source_path": "notes/2012/08/237904909436067840.md"
            
            , "syndicated": [{"type":"twitter","url":"https://twitter.com/roytang/statuses/237904909436067840/"},{"type":"facebook","url":"https://www.facebook.com/stephen.roy.tang/posts/10151808700823912"}]
            
            
            }
        
        , {
            "id": "https://mirror.roytang.net/2012/08/237802012115365889/",
            "url": "https://mirror.roytang.net/2012/08/237802012115365889/",
            "path": "/2012/08/237802012115365889/",
            "title": "",
            "content_html": "\u003cp\u003eWhile long weekends are relaxing, they might be bad for health. I eat a lot more when I\u0026rsquo;m at home =/\u003c/p\u003e\n",
            "summary": "While long weekends are relaxing, they might be bad for health. I eat a lot more when I\u0026rsquo;m at home =/",
            "date_published": "2012-08-21T06:43:12+00:00",
            "date_modified": "2019-09-01T15:11:18+08:00",
            "section": "notes",
            "source_path": "notes/2012/08/237802012115365889.md"
            
            , "syndicated": [{"type":"twitter","url":"https://twitter.com/roytang/statuses/237802012115365889/"}]
            
            
            }
        
        , {
            "id": "https://mirror.roytang.net/2012/08/237755231390281728/",
            "url": "https://mirror.roytang.net/2012/08/237755231390281728/",
            "path": "/2012/08/237755231390281728/",
            "title": "",
            "content_html": "\u003cp\u003eSad that we lose the good ones too soon. RIP Sec. Jesse Robredo\u003c/p\u003e\n",
            "summary": "Sad that we lose the good ones too soon. RIP Sec. Jesse Robredo",
            "date_published": "2012-08-21T03:37:19+00:00",
            "date_modified": "2019-09-12T04:21:53+08:00",
            "section": "notes",
            "source_path": "notes/2012/08/237755231390281728.md"
            
            , "syndicated": [{"type":"twitter","url":"https://twitter.com/roytang/statuses/237755231390281728/"},{"type":"facebook","url":"https://www.facebook.com/stephen.roy.tang/posts/10151807983258912"}]
            
            
            }
        
        , {
            "id": "https://mirror.roytang.net/2012/08/237738183692001282/",
            "url": "https://mirror.roytang.net/2012/08/237738183692001282/",
            "path": "/2012/08/237738183692001282/",
            "title": "",
            "content_html": "\u003cp\u003eRIP Sec. Rebredo. One of the best one we have.\u003c/p\u003e\n",
            "summary": "RIP Sec. Rebredo. One of the best one we have.",
            "date_published": "2012-08-21T02:29:34+00:00",
            "date_modified": "2020-08-18T17:19:06+08:00",
            "section": "notes",
            "source_path": "notes/2012/08/237738183692001282/index.md"
            
            , "syndicated": [{"type":"twitter","url":"https://twitter.com/roytang/statuses/237738183692001282/"}]
            
            
            }
        
        , {
            "id": "https://mirror.roytang.net/2012/08/237581848887316480/",
            "url": "https://mirror.roytang.net/2012/08/237581848887316480/",
            "path": "/2012/08/237581848887316480/",
            "title": "",
            "content_html": "\u003cp\u003eSummer slam on studio 23!\u003c/p\u003e\n",
            "summary": "Summer slam on studio 23!",
            "date_published": "2012-08-20T16:08:21+00:00",
            "date_modified": "2019-09-01T15:11:18+08:00",
            "section": "notes",
            "source_path": "notes/2012/08/237581848887316480.md"
            
            , "syndicated": [{"type":"twitter","url":"https://twitter.com/roytang/statuses/237581848887316480/"}]
            
            
            }
        
        , {
            "id": "https://mirror.roytang.net/2012/08/10151804510958912/",
            "url": "https://mirror.roytang.net/2012/08/10151804510958912/",
            "path": "/2012/08/10151804510958912/",
            "title": "",
            "content_html": "\u003cp\u003eBoo! Rich Hagon paasa lol\u003c/p\u003e\n",
            "summary": "Boo! Rich Hagon paasa lol",
            "date_published": "2012-08-19T22:32:00+00:00",
            "date_modified": "2019-09-28T15:27:19+08:00",
            "section": "notes",
            "source_path": "notes/2012/08/10151804510958912/index.md"
            
            , "syndicated": [{"type":"facebook","url":"https://www.facebook.com/stephen.roy.tang/posts/10151804510958912"}]
            
            
            }
        
        , {
            "id": "https://mirror.roytang.net/2012/08/237195404754694144/",
            "url": "https://mirror.roytang.net/2012/08/237195404754694144/",
            "path": "/2012/08/237195404754694144/",
            "title": "",
            "content_html": "\u003cp\u003e\u003ca href=\"https://twitter.com/aleksfelipe/\"\u003e@aleksfelipe\u003c/a\u003e wala na! :p\u003c/p\u003e\n",
            "summary": "@aleksfelipe wala na! :p",
            "date_published": "2012-08-19T14:32:46+00:00",
            "date_modified": "2020-01-23T05:14:22+08:00",
            "section": "notes",
            "source_path": "notes/2012/08/237195404754694144.md"
            
            , "syndicated": [{"type":"twitter","url":"https://twitter.com/roytang/statuses/237195404754694144/"}]
            
            
            }
        
        , {
            "id": "https://mirror.roytang.net/2012/08/237195263339556864/",
            "url": "https://mirror.roytang.net/2012/08/237195263339556864/",
            "path": "/2012/08/237195263339556864/",
            "title": "",
            "content_html": "\u003cp\u003eTeam Philippines eliminated in the #mtgwmc quarterfinals!  Boo to @mtgrich for the false hope :p\u003c/p\u003e\n",
            "summary": "Team Philippines eliminated in the #mtgwmc quarterfinals! Boo to @mtgrich for the false hope :p",
            "date_published": "2012-08-19T14:32:12+00:00",
            "date_modified": "2019-11-25T13:34:06+08:00",
            "section": "notes",
            "source_path": "notes/2012/08/237195263339556864.md"
            , "tags": ["mtgwmc","mtg"]
            , "syndicated": [{"type":"twitter","url":"https://twitter.com/roytang/statuses/237195263339556864/"}]
            
            
            }
        
        , {
            "id": "https://mirror.roytang.net/2012/08/237121208414515200/",
            "url": "https://mirror.roytang.net/2012/08/237121208414515200/",
            "path": "/2012/08/237121208414515200/",
            "title": "",
            "content_html": "\u003cp\u003eMTGO seems to have crashed when I tried to save a 5,000+ card deck. I wonder if I should file a bug report.\u003c/p\u003e\n",
            "summary": "MTGO seems to have crashed when I tried to save a 5,000+ card deck. I wonder if I should file a bug report.",
            "date_published": "2012-08-19T09:37:56+00:00",
            "date_modified": "2019-09-01T15:11:18+08:00",
            "section": "notes",
            "source_path": "notes/2012/08/237121208414515200.md"
            
            , "syndicated": [{"type":"twitter","url":"https://twitter.com/roytang/statuses/237121208414515200/"}]
            
            
            }
        
        , {
            "id": "https://mirror.roytang.net/2012/08/237116722224713729/",
            "url": "https://mirror.roytang.net/2012/08/237116722224713729/",
            "path": "/2012/08/237116722224713729/",
            "title": "",
            "content_html": "\u003cp\u003e\u003ca href=\"https://twitter.com/Yoshi_OnoChin/\"\u003e@Yoshi_OnoChin\u003c/a\u003e how come Street Fighter doesn\u0026rsquo;t have a dedicated story mode as good as Mortal Kombat\u0026rsquo;s? (Or any kind of story mode at all)\u003c/p\u003e\n",
            "summary": "@Yoshi_OnoChin how come Street Fighter doesn\u0026rsquo;t have a dedicated story mode as good as Mortal Kombat\u0026rsquo;s? (Or any kind of story mode at all)",
            "date_published": "2012-08-19T09:20:06+00:00",
            "date_modified": "2019-09-01T15:11:18+08:00",
            "section": "notes",
            "source_path": "notes/2012/08/237116722224713729.md"
            
            , "syndicated": [{"type":"twitter","url":"https://twitter.com/roytang/statuses/237116722224713729/"}]
            
            
            }
        
        , {
            "id": "https://mirror.roytang.net/2012/08/237095825350733824/",
            "url": "https://mirror.roytang.net/2012/08/237095825350733824/",
            "path": "/2012/08/237095825350733824/",
            "title": "",
            "content_html": "\u003cp\u003eOkay, i suck at mtgo today so i guess i should stop\u003c/p\u003e\n",
            "summary": "Okay, i suck at mtgo today so i guess i should stop",
            "date_published": "2012-08-19T07:57:04+00:00",
            "date_modified": "2019-09-01T15:11:18+08:00",
            "section": "notes",
            "source_path": "notes/2012/08/237095825350733824.md"
            
            , "syndicated": [{"type":"twitter","url":"https://twitter.com/roytang/statuses/237095825350733824/"}]
            
            
            }
        
        , {
            "id": "https://mirror.roytang.net/2012/08/237053246248714240/",
            "url": "https://mirror.roytang.net/2012/08/237053246248714240/",
            "path": "/2012/08/237053246248714240/",
            "title": "",
            "content_html": "\u003cp\u003eI treat shopping excursions like RPG quests. I just beeline to wherever the targets are and take them out one at a time. No browsing at all.\u003c/p\u003e\n",
            "summary": "I treat shopping excursions like RPG quests. I just beeline to wherever the targets are and take them out one at a time. No browsing at all.",
            "date_published": "2012-08-19T05:07:52+00:00",
            "date_modified": "2019-09-01T15:11:18+08:00",
            "section": "notes",
            "source_path": "notes/2012/08/237053246248714240.md"
            
            , "syndicated": [{"type":"twitter","url":"https://twitter.com/roytang/statuses/237053246248714240/"}]
            
            
            }
        
        , {
            "id": "https://mirror.roytang.net/2012/08/236985034597359616/",
            "url": "https://mirror.roytang.net/2012/08/236985034597359616/",
            "path": "/2012/08/236985034597359616/",
            "title": "",
            "content_html": "\u003cp\u003e\u003ca href=\"https://twitter.com/Dr_Jeebus/\"\u003e@Dr_Jeebus\u003c/a\u003e first time i\u0026rsquo;ve seen you stream. you sound nothing like that crazy old man on your avatar\u003c/p\u003e\n",
            "summary": "@Dr_Jeebus first time i\u0026rsquo;ve seen you stream. you sound nothing like that crazy old man on your avatar",
            "date_published": "2012-08-19T00:36:49+00:00",
            "date_modified": "2020-01-23T05:14:22+08:00",
            "section": "notes",
            "source_path": "notes/2012/08/236985034597359616.md"
            
            , "syndicated": [{"type":"twitter","url":"https://twitter.com/roytang/statuses/236985034597359616/"}]
            
            
            }
        
        , {
            "id": "https://mirror.roytang.net/2012/08/236972612520132608/",
            "url": "https://mirror.roytang.net/2012/08/236972612520132608/",
            "path": "/2012/08/236972612520132608/",
            "title": "",
            "content_html": "\u003cp\u003eTeam Philippines in the World Magic Cup Top 8! Go Philippines! #mtgwmc\u003c/p\u003e\n",
            "summary": "Team Philippines in the World Magic Cup Top 8! Go Philippines! #mtgwmc",
            "date_published": "2012-08-18T23:47:28+00:00",
            "date_modified": "2019-11-25T13:34:06+08:00",
            "section": "notes",
            "source_path": "notes/2012/08/236972612520132608.md"
            , "tags": ["mtgwmc","mtg"]
            , "syndicated": [{"type":"twitter","url":"https://twitter.com/roytang/statuses/236972612520132608/"}]
            
            
            }
        
        , {
            "id": "https://mirror.roytang.net/2012/08/236837291300118529/",
            "url": "https://mirror.roytang.net/2012/08/236837291300118529/",
            "path": "/2012/08/236837291300118529/",
            "title": "",
            "content_html": "\u003cp\u003eWatching Batman (1989). In an alternate world Burton and Keaton continued the series after Batman Returns. Perhaps a better world.\u003c/p\u003e\n",
            "summary": "Watching Batman (1989). In an alternate world Burton and Keaton continued the series after Batman Returns. Perhaps a better world.",
            "date_published": "2012-08-18T14:49:45+00:00",
            "date_modified": "2021-04-02T11:01:07+08:00",
            "section": "notes",
            "source_path": "notes/2012/08/236837291300118529/index.md"
            , "tags": ["movies"]
            , "syndicated": [{"type":"twitter","url":"https://twitter.com/roytang/statuses/236837291300118529/"},{"type":"facebook","url":"https://www.facebook.com/stephen.roy.tang/posts/10151802461213912"}]
            
            , "comments": [
                { 
                    "url": "https://www.facebook.com/stephen.roy.tang",
                    "source_file": "comment-20120818-000000-e3c66867-2d9d-4126-92d8-cec275d10a41.json"
                }
            ]
            }
        
        , {
            "id": "https://mirror.roytang.net/2012/08/236825380655353857/",
            "url": "https://mirror.roytang.net/2012/08/236825380655353857/",
            "path": "/2012/08/236825380655353857/",
            "title": "",
            "content_html": "\u003cp\u003eOkay, the PS3 youtube app is pretty sweet, seems a lot better than youtubing on the pc\u003c/p\u003e\n",
            "summary": "Okay, the PS3 youtube app is pretty sweet, seems a lot better than youtubing on the pc",
            "date_published": "2012-08-18T14:02:25+00:00",
            "date_modified": "2019-09-01T15:11:18+08:00",
            "section": "notes",
            "source_path": "notes/2012/08/236825380655353857.md"
            
            , "syndicated": [{"type":"twitter","url":"https://twitter.com/roytang/statuses/236825380655353857/"}]
            
            
            }
        
        , {
            "id": "https://mirror.roytang.net/2012/08/236815222147514368/",
            "url": "https://mirror.roytang.net/2012/08/236815222147514368/",
            "path": "/2012/08/236815222147514368/",
            "title": "",
            "content_html": "\u003cp\u003eQuora is good reading, but it seems difficult to navigate and chance upon the really well-written answers. Or maybe I dunno what i\u0026rsquo;m doing\u003c/p\u003e\n",
            "summary": "Quora is good reading, but it seems difficult to navigate and chance upon the really well-written answers. Or maybe I dunno what i\u0026rsquo;m doing",
            "date_published": "2012-08-18T13:22:03+00:00",
            "date_modified": "2019-09-01T15:11:18+08:00",
            "section": "notes",
            "source_path": "notes/2012/08/236815222147514368.md"
            
            , "syndicated": [{"type":"twitter","url":"https://twitter.com/roytang/statuses/236815222147514368/"}]
            
            
            }
        
        , {
            "id": "https://mirror.roytang.net/2012/08/236807478568968192/",
            "url": "https://mirror.roytang.net/2012/08/236807478568968192/",
            "path": "/2012/08/236807478568968192/",
            "title": "",
            "content_html": "\u003cp\u003eI don\u0026rsquo;t understand why a modern day banking website would restrict your password to 12 alphanumeric characters only\u003c/p\u003e\n",
            "summary": "I don\u0026rsquo;t understand why a modern day banking website would restrict your password to 12 alphanumeric characters only",
            "date_published": "2012-08-18T12:51:17+00:00",
            "date_modified": "2019-09-01T15:11:18+08:00",
            "section": "notes",
            "source_path": "notes/2012/08/236807478568968192.md"
            
            , "syndicated": [{"type":"twitter","url":"https://twitter.com/roytang/statuses/236807478568968192/"}]
            
            
            }
        
        , {
            "id": "https://mirror.roytang.net/2012/08/236783859432300544/",
            "url": "https://mirror.roytang.net/2012/08/236783859432300544/",
            "path": "/2012/08/236783859432300544/",
            "title": "",
            "content_html": "\u003cp\u003eRT @nhkcharm: Palace: \u0026ldquo;we ask the Filipino people to join the President and the cabinet in prayer for his successful rescue.\u0026rdquo;\u003c/p\u003e\n",
            "summary": "RT @nhkcharm: Palace: \u0026ldquo;we ask the Filipino people to join the President and the cabinet in prayer for his successful rescue.\u0026rdquo;",
            "date_published": "2012-08-18T11:17:25+00:00",
            "date_modified": "2020-08-09T02:41:23+08:00",
            "section": "notes",
            "source_path": "notes/2012/08/236783859432300544/index.md"
            
            , "syndicated": [{"type":"twitter","url":"https://twitter.com/roytang/statuses/236783859432300544/"}]
            
            
            }
        
        , {
            "id": "https://mirror.roytang.net/2012/08/236781523230138369/",
            "url": "https://mirror.roytang.net/2012/08/236781523230138369/",
            "path": "/2012/08/236781523230138369/",
            "title": "",
            "content_html": "\u003cp\u003eDILG Sec. Robredo\u0026rsquo;s plane crashed near the Masbate airport. =(\u003c/p\u003e\n",
            "summary": "DILG Sec. Robredo\u0026rsquo;s plane crashed near the Masbate airport. =(",
            "date_published": "2012-08-18T11:08:08+00:00",
            "date_modified": "2019-09-12T04:21:53+08:00",
            "section": "notes",
            "source_path": "notes/2012/08/236781523230138369.md"
            
            , "syndicated": [{"type":"twitter","url":"https://twitter.com/roytang/statuses/236781523230138369/"},{"type":"facebook","url":"https://www.facebook.com/stephen.roy.tang/posts/10151802155868912"}]
            
            
            }
        
        , {
            "id": "https://mirror.roytang.net/2012/08/236669041333383168/",
            "url": "https://mirror.roytang.net/2012/08/236669041333383168/",
            "path": "/2012/08/236669041333383168/",
            "title": "",
            "content_html": "\u003cp\u003eWoah, Team Philippines finished Day 1 of the World Magic Cup at 7th place, advancing to Day 2. Good job! #inggit\u003c/p\u003e\n",
            "summary": "Woah, Team Philippines finished Day 1 of the World Magic Cup at 7th place, advancing to Day 2. Good job! #inggit",
            "date_published": "2012-08-18T03:41:11+00:00",
            "date_modified": "2019-09-07T03:37:00+08:00",
            "section": "notes",
            "source_path": "notes/2012/08/236669041333383168.md"
            , "tags": ["inggit"]
            , "syndicated": [{"type":"twitter","url":"https://twitter.com/roytang/statuses/236669041333383168/"}]
            
            
            }
        
        , {
            "id": "https://mirror.roytang.net/2012/08/236524347022536704/",
            "url": "https://mirror.roytang.net/2012/08/236524347022536704/",
            "path": "/2012/08/236524347022536704/",
            "title": "",
            "content_html": "\u003cp\u003eSup spelldashers.\u003c/p\u003e\n",
            "summary": "Sup spelldashers.",
            "date_published": "2012-08-17T18:06:13+00:00",
            "date_modified": "2020-08-09T02:33:21+08:00",
            "section": "notes",
            "source_path": "notes/2012/08/236524347022536704/index.md"
            
            , "syndicated": [{"type":"twitter","url":"https://twitter.com/roytang/statuses/236524347022536704/"}]
            
            
            }
        
        , {
            "id": "https://mirror.roytang.net/2012/08/236111220606914561/",
            "url": "https://mirror.roytang.net/2012/08/236111220606914561/",
            "path": "/2012/08/236111220606914561/",
            "title": "",
            "content_html": "\u003cp\u003e\u0026ldquo;Manila is the most densely populated city in the world\u0026rdquo; \u003ca href=\"http://1.usa.gov/Q3ex5c\"\u003ehttp://1.usa.gov/Q3ex5c\u003c/a\u003e\u003c/p\u003e\n",
            "summary": "\u0026ldquo;Manila is the most densely populated city in the world\u0026rdquo; http://1.usa.gov/Q3ex5c",
            "date_published": "2012-08-16T14:44:36+00:00",
            "date_modified": "2021-04-16T18:43:32+08:00",
            "section": "notes",
            "source_path": "notes/2012/08/236111220606914561/index.md"
            
            , "syndicated": [{"type":"twitter","url":"https://twitter.com/roytang/statuses/236111220606914561/"},{"type":"facebook","url":"https://www.facebook.com/stephen.roy.tang/posts/10151798413178912"}]
            
            , "comments": [
                { 
                    "url": "https://twitter.com/rocketkeis",
                    "source_file": "comment-20120816-153140-26b70e63-a5eb-40be-b39d-4add5517fa0c.json"
                }, { 
                    "url": "https://twitter.com/roytang",
                    "source_file": "comment-20120816-232037-77794ece-44c2-4a85-9adc-c87ba317c8d5.json"
                }
            ]
            }
        
        , {
            "id": "https://mirror.roytang.net/2012/08/236081722872168448/",
            "url": "https://mirror.roytang.net/2012/08/236081722872168448/",
            "path": "/2012/08/236081722872168448/",
            "title": "",
            "content_html": "\u003cp\u003eWoohoo my GP manila prize check came in\u003c/p\u003e\n",
            "summary": "Woohoo my GP manila prize check came in",
            "date_published": "2012-08-16T12:47:23+00:00",
            "date_modified": "2021-04-16T11:10:08+08:00",
            "section": "notes",
            "source_path": "notes/2012/08/236081722872168448/index.md"
            
            , "syndicated": [{"type":"twitter","url":"https://twitter.com/roytang/statuses/236081722872168448/"}]
            
            , "comments": [
                { 
                    "url": "https://twitter.com/aleksfelipe",
                    "source_file": "comment-20120816-125653-66614b87-284a-4c7f-80d5-e45e05583291.json"
                }, { 
                    "url": "https://twitter.com/roytang",
                    "source_file": "comment-20120816-142118-97c79246-283f-440f-9efe-d0b507ce7dc4.json"
                }
            ]
            }
        
        , {
            "id": "https://mirror.roytang.net/2012/08/235881867008692225/",
            "url": "https://mirror.roytang.net/2012/08/235881867008692225/",
            "path": "/2012/08/235881867008692225/",
            "title": "",
            "content_html": "\u003cp\u003e\u003ca href=\"https://twitter.com/leya12/\"\u003e@leya12\u003c/a\u003e waiting shed :p\u003c/p\u003e\n",
            "summary": "@leya12 waiting shed :p",
            "date_published": "2012-08-15T23:33:14+00:00",
            "date_modified": "2020-01-23T05:14:22+08:00",
            "section": "notes",
            "source_path": "notes/2012/08/235881867008692225.md"
            
            , "syndicated": [{"type":"twitter","url":"https://twitter.com/roytang/statuses/235881867008692225/"}]
            
            
            }
        
        , {
            "id": "https://mirror.roytang.net/2012/08/235880508087730176/",
            "url": "https://mirror.roytang.net/2012/08/235880508087730176/",
            "path": "/2012/08/235880508087730176/",
            "title": "",
            "content_html": "\u003cp\u003e\u003ca href=\"https://twitter.com/roytang/\"\u003e@roytang\u003c/a\u003e Happy 4th TwBirthday! You\u0026rsquo;ve been around since 17 August 2008! \u003ca href=\"http://twbirthday.com/roytang/\"\u003ehttp://twbirthday.com/roytang/\u003c/a\u003e\u003c/p\u003e\n",
            "summary": "@roytang Happy 4th TwBirthday! You\u0026rsquo;ve been around since 17 August 2008! http://twbirthday.com/roytang/",
            "date_published": "2012-08-15T23:27:50+00:00",
            "date_modified": "2020-07-14T23:20:57+08:00",
            "section": "notes",
            "source_path": "notes/2012/08/235880508087730176/index.md"
            
            , "syndicated": [{"type":"twitter","url":"https://twitter.com/roytang/statuses/235880508087730176/"}]
            
            
            }
        
        , {
            "id": "https://mirror.roytang.net/2012/08/y9i12/",
            "url": "https://mirror.roytang.net/2012/08/y9i12/",
            "path": "/2012/08/y9i12/",
            "title": "",
            "content_html": "\u003ch4 id=\"posted-on-rcomicbooks-question-about-the-new-52-robinshttpsredditcomrcomicbookscommentsy9i12question_about_the_new_52_robins\"\u003ePosted on r/comicbooks: \u003ca href=\"https://reddit.com/r/comicbooks/comments/y9i12/question_about_the_new_52_robins/\"\u003eQuestion about the new 52 Robins\u003c/a\u003e\u003c/h4\u003e\n\u003cp\u003eDo we know their current ages and when they became Robin, and for how long? I mean, I know Damian is ten years old right now. And Dick is always drawn like he\u0026rsquo;s maybe 21 or something? But given that Dick started being Robin at around 9 or 10, that means Batman has been Batman for more than a decade?\u003c/p\u003e\n\u003cp\u003eObviously it\u0026rsquo;s all \u0026ldquo;comic book time\u0026rdquo;, but I just want to get an idea of how long ago and for what duration each of them (Dick, Jason, Tim, Damian) were Robin in the New 52 universe.\u003c/p\u003e\n",
            "summary": "Posted on r/comicbooks: Question about the new 52 Robins Do we know their current ages and when they became Robin, and for how long? I mean, I know Damian is ten years old right now. And Dick is always drawn like he\u0026rsquo;s maybe 21 or something? But given that Dick started being Robin at around 9 or 10, that means Batman has been Batman for more than a decade?\nObviously it\u0026rsquo;s all \u0026ldquo;comic book time\u0026rdquo;, but I just want to get an idea of how long ago and for what duration each of them (Dick, Jason, Tim, Damian) were Robin in the New 52 universe.",
            "date_published": "2012-08-15T23:01:06+00:00",
            "date_modified": "2020-01-23T03:46:15+08:00",
            "section": "notes",
            "source_path": "notes/2012/08/y9i12/index.md"
            , "tags": ["comics"]
            , "syndicated": [{"type":"reddit","url":"https://reddit.com/r/comicbooks/comments/y9i12/question_about_the_new_52_robins/"}]
            
            
            }
        
        , {
            "id": "https://mirror.roytang.net/2012/08/y9ee7/",
            "url": "https://mirror.roytang.net/2012/08/y9ee7/",
            "path": "/2012/08/y9ee7/",
            "title": "",
            "content_html": "\u003ch4 id=\"posted-on-raskreddit-if-you-had-a-chance-to-relive-your-life-from-a-previous-point-in-time-retaining-all-your-current-knowledge-a-would-you-do-it-and-b-what-point-would-you-choose-to-go-back-to-httpsredditcomraskredditcommentsy9ee7if_you_had_a_chance_to_relive_your_life_from_a\"\u003ePosted on r/AskReddit: \u003ca href=\"https://reddit.com/r/AskReddit/comments/y9ee7/if_you_had_a_chance_to_relive_your_life_from_a/\"\u003eif you had a chance to relive your life from a previous point in time retaining all your current knowledge, (a) would you do it and (b) what point would you choose to go back to? \u003c/a\u003e\u003c/h4\u003e\n",
            "summary": "Posted on r/AskReddit: if you had a chance to relive your life from a previous point in time retaining all your current knowledge, (a) would you do it and (b) what point would you choose to go back to?  ",
            "date_published": "2012-08-15T21:49:25+00:00",
            "date_modified": "2020-01-23T03:46:15+08:00",
            "section": "notes",
            "source_path": "notes/2012/08/y9ee7/index.md"
            , "tags": ["askreddit"]
            , "syndicated": [{"type":"reddit","url":"https://reddit.com/r/AskReddit/comments/y9ee7/if_you_had_a_chance_to_relive_your_life_from_a/"}]
            
            
            }
        
        , {
            "id": "https://mirror.roytang.net/2012/08/10151796201148912/",
            "url": "https://mirror.roytang.net/2012/08/10151796201148912/",
            "path": "/2012/08/10151796201148912/",
            "title": "",
            "content_html": "\u003cp\u003eif you had a chance to relive your life from a previous point in time retaining all your current knowledge, (a) would you do it and (b) what point would you choose to go back to?\u003c/p\u003e\n",
            "summary": "if you had a chance to relive your life from a previous point in time retaining all your current knowledge, (a) would you do it and (b) what point would you choose to go back to?",
            "date_published": "2012-08-15T21:45:00+00:00",
            "date_modified": "2019-09-28T15:27:19+08:00",
            "section": "notes",
            "source_path": "notes/2012/08/10151796201148912/index.md"
            
            , "syndicated": [{"type":"facebook","url":"https://www.facebook.com/stephen.roy.tang/posts/10151796201148912"}]
            
            , "comments": [
                { 
                    "url": "https://www.facebook.com/jvee.veneracion",
                    "source_file": "comment-20120815-000000-ae8944a1-3fb2-4f35-bb76-c88ef61a81c7.json"
                }, { 
                    "url": "https://www.facebook.com/stephen.roy.tang",
                    "source_file": "comment-20120815-000001-f1dc697b-218d-4330-8735-7349db9d35ac.json"
                }, { 
                    "url": "https://www.facebook.com/zianofzin",
                    "source_file": "comment-20120815-000002-82acf6aa-cfdb-4fcb-987f-f836f624eec5.json"
                }, { 
                    "url": "https://www.facebook.com/jaime.l.garcia.779",
                    "source_file": "comment-20120815-000003-c46ac00f-304e-46b3-bcab-fcc282af3cef.json"
                }, { 
                    "url": "https://www.facebook.com/raymond.lirag",
                    "source_file": "comment-20120816-000004-74a3f8ae-055a-422a-882b-58e89bd226da.json"
                }
            ]
            }
        
    ]
     , "prev": "/p/250/feed.json" 
     , "next": "/p/252/feed.json" 
}